prettylog.py
prettylog-0.3.0.dist-info/METADATA
prettylog-0.3.0.dist-info/RECORD
prettylog-0.3.0.dist-info/WHEEL
prettylog-0.3.0.dist-info/top_level.txt
